odoo/addons/purchase_order_archive/README.rst
odoo/addons/purchase_order_archive/__init__.py
odoo/addons/purchase_order_archive/__manifest__.py
odoo/addons/purchase_order_archive/i18n/es.po
odoo/addons/purchase_order_archive/i18n/it.po
odoo/addons/purchase_order_archive/i18n/pt_BR.po
odoo/addons/purchase_order_archive/i18n/purchase_order_archive.pot
odoo/addons/purchase_order_archive/i18n/zh_CN.po
odoo/addons/purchase_order_archive/models/__init__.py
odoo/addons/purchase_order_archive/models/purchase_order.py
odoo/addons/purchase_order_archive/readme/CONTRIBUTORS.md
odoo/addons/purchase_order_archive/readme/DESCRIPTION.md
odoo/addons/purchase_order_archive/readme/USAGE.md
odoo/addons/purchase_order_archive/setup/purchase_order_archive/setup.py
odoo/addons/purchase_order_archive/setup/purchase_order_archive/odoo/addons/purchase_order_archive
odoo/addons/purchase_order_archive/static/description/icon.png
odoo/addons/purchase_order_archive/static/description/index.html
odoo/addons/purchase_order_archive/tests/__init__.py
odoo/addons/purchase_order_archive/tests/test_purchase_order_archive.py
odoo/addons/purchase_order_archive/views/purchase_order.xml
odoo_addon_purchase_order_archive-18.0.1.0.0.6.dist-info/METADATA
odoo_addon_purchase_order_archive-18.0.1.0.0.6.dist-info/WHEEL
odoo_addon_purchase_order_archive-18.0.1.0.0.6.dist-info/top_level.txt
odoo_addon_purchase_order_archive-18.0.1.0.0.6.dist-info/RECORD
